arts_localisation/__init__.py
arts_localisation/__version__.py
arts_localisation/calc_snr.py
arts_localisation/config_parser.py
arts_localisation/constants.py
arts_localisation/get_angles.py
arts_localisation/get_hadec.py
arts_localisation/plot_mb.py
arts_localisation/run_localisation.py
arts_localisation/square_39p1.cb_offsets
arts_localisation/tools.py
arts_localisation/visualise.py
arts_localisation/beam_models/__init__.py
arts_localisation/beam_models/beam_models_190607.csv
arts_localisation/beam_models/beamformer.py
arts_localisation/beam_models/compound_beam.py
arts_localisation/beam_models/sb_generator.py
arts_localisation/beam_models/sbtable-sc4-12tabs-71sbs.txt
arts_localisation/beam_models/simulate_cb_pattern.py
arts_localisation/beam_models/simulate_sb_pattern.py
arts_localisation/data_tools/__init__.py
arts_localisation/data_tools/filterbank_reader.py
arts_localisation/data_tools/snr_tools.py
arts_localisation/data_tools/spectra.py
arts_localisation-1.0.dist-info/LICENSE
arts_localisation-1.0.dist-info/METADATA
arts_localisation-1.0.dist-info/WHEEL
arts_localisation-1.0.dist-info/entry_points.txt
arts_localisation-1.0.dist-info/top_level.txt
arts_localisation-1.0.dist-info/RECORD
